enrobocode/__init__.py
enrobocode/nodemcu.py
enrobocode/speaker.py
enrobocode-0.2.0.dist-info/METADATA
enrobocode-0.2.0.dist-info/WHEEL
enrobocode-0.2.0.dist-info/top_level.txt
enrobocode-0.2.0.dist-info/RECORD
