Metadata-Version: 2.4
Name: enrobocode
Version: 0.2.0
Summary: English Robot Code — control robots easily
Author: Your Name
Requires-Python: >=3.6
Requires-Dist: InquirerPy
Dynamic: author
Dynamic: requires-dist
Dynamic: requires-python
Dynamic: summary
